fw_gear_freesurfer_recon_all/__init__.py
fw_gear_freesurfer_recon_all/main.py
fw_gear_freesurfer_recon_all/parser.py
fw_gear_freesurfer_recon_all-2.0.1.dist-info/LICENSE
fw_gear_freesurfer_recon_all-2.0.1.dist-info/METADATA
fw_gear_freesurfer_recon_all-2.0.1.dist-info/WHEEL
fw_gear_freesurfer_recon_all-2.0.1.dist-info/RECORD
